pid_controller.v
module pid_controller (
    input clk,
    input rst,
    input signed [15:0] setpoint,
    input signed [15:0] feedback,
    input signed [15:0] kp,
    input signed [15:0] ki,
    input signed [15:0] kd,
    output reg signed [15:0] control_out
);

    reg signed [15:0] error;
    reg signed [15:0] integral;
    reg signed [15:0] last_error;
    wire signed [15:0] derivative;

    assign derivative = error - last_error;

    always @(posedge clk or posedge rst) begin
        if (rst) begin
            error <= 0;
            integral <= 0;
            last_error <= 0;
            control_out <= 0;
        end else begin
            error <= setpoint - feedback;
            integral <= integral + error;
            last_error <= error;
            control_out <= (kp * error) + (ki * integral) + (kd * derivative);
        end
    end

endmodule

dump.vcd
$version Generated by VerilatedVcd $end
$timescale 1ps $end
 $scope module $rootio $end
  $var wire 1 # clk $end
  $var wire 1 $ rst $end
  $var wire 16 % setpoint [15:0] $end
  $var wire 16 & feedback [15:0] $end
  $var wire 16 ' kp [15:0] $end
  $var wire 16 ( ki [15:0] $end
  $var wire 16 ) kd [15:0] $end
  $var wire 16 * control_out [15:0] $end
 $upscope $end
 $scope module pid_controller $end
  $var wire 1 + clk $end
  $var wire 1 , rst $end
  $var wire 16 - setpoint [15:0] $end
  $var wire 16 . feedback [15:0] $end
  $var wire 16 / kp [15:0] $end
  $var wire 16 0 ki [15:0] $end
  $var wire 16 1 kd [15:0] $end
  $var wire 16 2 control_out [15:0] $end
  $var wire 16 3 error [15:0] $end
  $var wire 16 4 integral [15:0] $end
  $var wire 16 5 last_error [15:0] $end
  $var wire 16 6 derivative [15:0] $end
 $upscope $end
$enddefinitions $end


#0
1#
0$
b0000000000000000 %
b0000000000000000 &
b0000000000000000 '
b0000000000000000 (
b0000000000000000 )
b0000000000000000 *
1+
0,
b0000000000000000 -
b0000000000000000 .
b0000000000000000 /
b0000000000000000 0
b0000000000000000 1
b0000000000000000 2
b0000000000000000 3
b0000000000000000 4
b0000000000000000 5
b0000000000000000 6
#5000
0#
0+
#10000
1#
b0000000001100100 %
b0000000000110010 &
b0000000000000010 '
1+
b0000000001100100 -
b0000000000110010 .
b0000000000000010 /
#15000
0#
0+
#20000
1#
1+
b0000000000110010 3
b0000000000110010 6
#25000
0#
0+
#30000
1#
b0000000001100100 *
1+
b0000000001100100 2
b0000000000110010 4
b0000000000110010 5
b0000000000000000 6
#35000
0#
0+
#40000
1#
1+
b0000000001100100 4
#45000
0#
0+
#50000
1#
1+
b0000000010010110 4
#55000
0#
0+
#60000
1#
1+
b0000000011001000 4
#65000
0#
0+
#70000
1#
1+
b0000000011111010 4
#75000
0#
0+
#80000
1#
1+
b0000000100101100 4
